CHANGES.txt
COPYRIGHT.txt
LICENSE.txt
README.txt
bootstrap.py
buildout.cfg
setup.py
src/zamplugin/__init__.py
src/zamplugin.control.egg-info/PKG-INFO
src/zamplugin.control.egg-info/SOURCES.txt
src/zamplugin.control.egg-info/dependency_links.txt
src/zamplugin.control.egg-info/namespace_packages.txt
src/zamplugin.control.egg-info/not-zip-safe
src/zamplugin.control.egg-info/requires.txt
src/zamplugin.control.egg-info/top_level.txt
src/zamplugin/control/README.txt
src/zamplugin/control/__init__.py
src/zamplugin/control/app.zcml
src/zamplugin/control/applicationcontrol.py
src/zamplugin/control/configure.zcml
src/zamplugin/control/ftesting.zcml
src/zamplugin/control/menu.py
src/zamplugin/control/menu.zcml
src/zamplugin/control/namespace.py
src/zamplugin/control/plugin.py
src/zamplugin/control/plugin.zcml
src/zamplugin/control/tests.py
src/zamplugin/control/browser/__init__.py
src/zamplugin/control/browser/configure.zcml
src/zamplugin/control/browser/generation.py
src/zamplugin/control/browser/generation_details.pt
src/zamplugin/control/browser/generations.pt
src/zamplugin/control/browser/runtimeinfo.pt
src/zamplugin/control/browser/runtimeinfo.py
src/zamplugin/control/browser/zodbcontrol.pt
src/zamplugin/control/browser/zodbcontrol.py